README.rst
setup.py
src/gsimporter/__init__.py
src/gsimporter/_util.py
src/gsimporter/api.py
src/gsimporter/client.py
src/gsimporter.egg-info/PKG-INFO
src/gsimporter.egg-info/SOURCES.txt
src/gsimporter.egg-info/dependency_links.txt
src/gsimporter.egg-info/requires.txt
src/gsimporter.egg-info/top_level.txt