Metadata-Version: 1.0
Name: gsimporter
Version: 1.0.0
Summary: GeoServer Importer Client
Home-page: https://github.com/opengeo/gsimporter
Author: Ian Schneider
Author-email: ischneider@opengeo.org
License: MIT
Keywords: GeoServer Importer
Platform: UNKNOWN
